cornerplots.py
cornerplots-1.0.dist-info/WHEEL
cornerplots-1.0.dist-info/METADATA
cornerplots-1.0.dist-info/RECORD
