Metadata-Version: 2.1
Name: cornerplots
Version: 1.0
Summary: Simple library to create corner plots in `matplotlib`.
Author-email: Mathieu Daëron <daeron@lsce.ipsl.fr>
Requires-Python: >=3.11
Classifier: License :: OSI Approved :: MIT License
Requires-Dist: matplotlib >= 3.8
Project-URL: Home, https://github.com/mdaeron/cornerplots
